seave/__init__.py
seave/comorbidities.py
seave/pandemic.py
seave/study.py
seave/cli/__init__.py
seave/cli/cli.py
SEAVE-0.0.4.dist-info/METADATA
SEAVE-0.0.4.dist-info/WHEEL
SEAVE-0.0.4.dist-info/entry_points.txt
SEAVE-0.0.4.dist-info/top_level.txt
SEAVE-0.0.4.dist-info/RECORD
